Metadata-Version: 2.1
Name: e2fyi-pyspark
Version: 0.1.0a1
Summary: Productivity functions for common but painful pyspark tasks.
Home-page: https://github.com/e2fyi/pyspark-utils
Author: eterna2
Author-email: eterna2@hotmail.com
License: UNKNOWN
Keywords: util pyspark
Platform: UNKNOWN
Classifier: Development Status :: 2 - Pre-Alpha
Classifier: Intended Audience :: Developers
Classifier: Natural Language :: English
Classifier: Programming Language :: Python :: 3
Classifier: Programming Language :: Python :: 3.6
Classifier: Programming Language :: Python :: 3.7
Requires-Python: >=3.6
